[
    {
        "NodeName": "OpenNeuro",
        "ApiURL": "https://openneuro.neurobagel.org/node" 
    },
    {
        "NodeName": "Quebec Parkinson Network",
        "ApiURL": "https://qpn.neurobagel.org/node" 
    },
    {
        "NodeName": "International Neuroimaging Data-sharing Initiative",
        "ApiURL": "https://indi.neurobagel.org/node" 
    },
    {
        "NodeName": "Austrian Neurocloud",
        "ApiURL": "https://neurobagel.anc.plus.ac.at/napi"
    },
    {
        "NodeName": "EBRAINS",
        "ApiURL": "https://ebrains.neurobagel.org/node"
    },
    {
        "NodeName": "Ontario Brain Institute",
        "ApiURL": "https://nb-api.obicloud.ca/"
    }
]
